{
    "has_more": true,
    "data": [        
        {
            "media_name": "三联生活周刊",
            "ban_comment": 0,
            "abstract": "可能因为老张写给山田喜美子信里的几句话：你的长头发剪了没有做梦都看你在梳头我是多么喜欢你的长头发唷▲ 1955年张大千在日本举办画展留影，右一为山田喜美子 出自张大千文献展。",
            "image_list": [
                {
                    "url": "http://p1-tt-ipv6.byteimg.com/img/pgc-image/0a1c99dbc0474216a16b5fb79516449f~tplv-tt-cs0:640:360.jpg",
                    "width": 640,
                    "height": 360
                },
                {
                    "url": "http://p26-tt.byteimg.com/img/pgc-image/ca8dc4e3891a483f9d8dbf2ebb835fdc~tplv-tt-cs0:640:321.jpg",
                    "width": 640,
                    "height": 321
                },
                {
                    "url": "http://p26-tt.byteimg.com/img/pgc-image/b3125c5551fa4707921667cdc333cf06~tplv-tt-cs0:640:812.jpg",
                    "width": 640,
                    "height": 360
                }
            ],
            "datetime": "2020-04-03 15:39",
            "article_type": 0,
            "more_mode": true,
            "tag": "news_culture",
            "has_m3u8_video": 0,
            "display_dt": 1585823581,
            "has_mp4_video": 0,
            "aggr_type": 1,
            "cell_type": 0,
            "article_sub_type": 0,
            "bury_count": 0,
            "title": "张大千逝世37周年| 大千先生笔下的女性形象，和与喜美子的“东京爱情故事”",
            "source_icon_style": 1,
            "tip": 0,
            "has_video": false,
            "share_url": "http://toutiao.com/a6811060417507361287/?app=news_article&is_hit_share_recommend=0",
            "source": "三联生活周刊",
            "comment_count": 24,
            "article_url": "http://toutiao.com/group/6811060417507361287/",
            "publish_time": 1585823581,
            "group_flags": 0,
            "gallary_image_count": 18,
            "action_extra": "{\"channel_id\": 0}",
            "tag_id": "6811060417507361287",
            "source_url": "/i6811060417507361287/",
            "display_url": "http://toutiao.com/group/6811060417507361287/",
            "is_stick": false,
            "item_id": "6811060417507361287",
            "repin_count": 78,
            "cell_flag": 262155,
            "source_open_url": "sslocal://profile?uid=67693543807",
            "level": 0,
            "digg_count": 88,
            "behot_time": 1585899544,
            "hot": 0,
            "cursor": 1585899544999,
            "url": "http://toutiao.com/group/6811060417507361287/",
            "like_count": 76,
            "user_repin": 0,
            "has_image": true,
            "video_style": 0,
            "media_info": {
                "avatar_url": "http://p2.pstatp.com/large/382c000fbf301ddc6d1a",
                "media_id": 1577337153201166,
                "name": "三联生活周刊",
                "user_verified": true
            },
            "group_id": "6811060417507361287"
        },
        {
            "media_name": "中国网",
            "ban_comment": 0,
            "abstract": "证券时报记者左江从派出所做完笔录出来，关女士倚着墙站了很久。自去年5月奔波至今，她已感到心力交瘁，但仍不敢有丝毫懈怠。",
            "image_list": [
                {
                    "url": "http://p9-tt-ipv6.byteimg.com/img/pgc-image/Rv3QEpeC4UyTZS~tplv-tt-cs0:640:360.jpg",
                    "width": 640,
                    "height": 360
                },
                {
                    "url": "http://p29-tt.byteimg.com/img/pgc-image/Rv3QEq7A02rscf~tplv-tt-cs0:600:270.jpg",
                    "width": 600,
                    "height": 270
                },
                {
                    "url": "http://p6-tt-ipv6.byteimg.com/img/pgc-image/Rv3QEqYCQ1xIPe~tplv-tt-cs0:600:642.jpg",
                    "width": 600,
                    "height": 337
                }
            ],
            "datetime": "2020-04-03 15:31",
            "article_type": 0,
            "more_mode": true,
            "tag": "news_finance",
            "has_m3u8_video": 0,
            "display_dt": 1585876517,
            "has_mp4_video": 0,
            "aggr_type": 1,
            "cell_type": 0,
            "article_sub_type": 0,
            "bury_count": 0,
            "title": "​私募爆雷数亿元下落不明 五百投资者艰难追偿",
            "source_icon_style": 1,
            "tip": 0,
            "has_video": false,
            "share_url": "http://toutiao.com/group/6811287776277824008/?app=news_article&is_hit_share_recommend=0",
            "source": "中国网",
            "comment_count": 10,
            "article_url": "https://m.china.com.cn/appshare/doc_1_11_1579001.html",
            "publish_time": 1585876517,
            "group_flags": 0,
            "gallary_image_count": 4,
            "action_extra": "{\"channel_id\": 0}",
            "tag_id": "6811287776277824008",
            "source_url": "/i6811287776277824008/",
            "display_url": "http://toutiao.com/group/6811287776277824008/",
            "is_stick": false,
            "item_id": "6811287776277824008",
            "repin_count": 87,
            "cell_flag": 262155,
            "source_open_url": "sslocal://profile?uid=3350881978",
            "level": 0,
            "digg_count": 231,
            "behot_time": 1585899094,
            "hot": 0,
            "cursor": 1585899094999,
            "url": "https://m.china.com.cn/appshare/doc_1_11_1579001.html",
            "like_count": 158,
            "user_repin": 0,
            "has_image": true,
            "video_style": 0,
            "media_info": {
                "avatar_url": "http://p2.pstatp.com/large/3826/6579485293",
                "media_id": 3359968622,
                "name": "中国网",
                "user_verified": true
            },
            "group_id": "6811287776277824008"
        },        
        {
            "media_name": "新华社",
            "ban_comment": 0,
            "abstract": "随着清明节的临近，浙江省金华市武义县10多万亩茶园新芽勃发、满山翠绿，光凭手工采摘难以赶上节气。以上图为：2020年4月2日，浙江省金华市武义县各地茶农用采茶机在茶园抢采明前茶。",
            "image_list": [
                {
                    "url": "http://p29-tt.byteimg.com/img/pgc-image/Rv3IGLvFBqhrZy~tplv-tt-cs0:640:360.jpg",
                    "width": 640,
                    "height": 360
                },
                {
                    "url": "http://p6-tt-ipv6.byteimg.com/img/pgc-image/Rv3IGMn7S9soZZ~tplv-tt-cs0:1000:750.jpg",
                    "width": 1000,
                    "height": 562
                },
                {
                    "url": "http://p26-tt.byteimg.com/img/pgc-image/Rv3IGNp6ZKSYGe~tplv-tt-cs0:1000:750.jpg",
                    "width": 1000,
                    "height": 562
                }
            ],
            "datetime": "2020-04-03 15:01",
            "article_type": 0,
            "more_mode": true,
            "tag": "news_agriculture",
            "has_m3u8_video": 0,
            "display_dt": 1585874667,
            "has_mp4_video": 0,
            "aggr_type": 1,
            "cell_type": 0,
            "article_sub_type": 0,
            "bury_count": 0,
            "title": "浙江武义：机器换人抢采明前茶",
            "source_icon_style": 1,
            "tip": 0,
            "has_video": false,
            "share_url": "http://toutiao.com/group/6811279832022778376/?app=news_article&is_hit_share_recommend=0",
            "source": "新华社",
            "comment_count": 84,
            "article_url": "http://api.xinhua-news.com/newroute/newsdetail/101002020040200003631?dest=AlnhelSPdSwmH8YZjbrho3rkaUWfBCrmfD1X0R6ES6hc",
            "publish_time": 1585874667,
            "group_flags": 0,
            "gallary_image_count": 7,
            "action_extra": "{\"channel_id\": 0}",
            "tag_id": "6811279832022778376",
            "source_url": "/i6811279832022778376/",
            "display_url": "http://toutiao.com/group/6811279832022778376/",
            "is_stick": false,
            "item_id": "6811279832022778376",
            "repin_count": 32,
            "cell_flag": 262155,
            "source_open_url": "sslocal://profile?uid=5757425042",
            "level": 0,
            "digg_count": 49,
            "behot_time": 1585897294,
            "hot": 0,
            "cursor": 1585897294999,
            "url": "http://api.xinhua-news.com/newroute/newsdetail/101002020040200003631?dest=AlnhelSPdSwmH8YZjbrho3rkaUWfBCrmfD1X0R6ES6hc",
            "like_count": 51,
            "user_repin": 0,
            "has_image": true,
            "video_style": 0,
            "media_info": {
                "avatar_url": "http://p2.pstatp.com/large/9519/925052030",
                "media_id": 5757425042,
                "name": "新华社",
                "user_verified": true
            },
            "group_id": "6811279832022778376"
        },
        {
            "media_name": "新华网客户端",
            "ban_comment": 0,
            "abstract": "来源:新华社“新华视点”微博中共中央总书记、国家主席、中央军委主席习近平3日上午在参加首都义务植树活动时强调，在全国疫情防控形势持续向好、复工复产不断推进的时刻，我们一起参加义务植树，既是以实际行动促进经济社会发展和生产生活秩序加快恢复，又是倡导尊重自然、爱护自然的生态文明理念，",
            "image_list": [],
            "datetime": "2020-04-03 18:42",
            "article_type": 0,
            "tag": "news_politics",
            "has_m3u8_video": 0,
            "display_dt": 1585907283,
            "has_mp4_video": 0,
            "aggr_type": 1,
            "cell_type": 0,
            "article_sub_type": 0,
            "bury_count": 0,
            "title": "习近平参加首都义务植树活动",
            "source_icon_style": 1,
            "tip": 0,
            "has_video": false,
            "share_url": "http://toutiao.com/group/6811419918387380750/?app=news_article&is_hit_share_recommend=0",
            "label": "置顶",
            "source": "新华网客户端",
            "comment_count": 42,
            "article_url": "http://www.xinhuanet.com/politics/leaders/2020-04/03/c_1125811258.htm",
            "publish_time": 1585907283,
            "group_flags": 0,
            "has_image": false,
            "action_extra": "{\"channel_id\": 0}",
            "tag_id": "6811419918387380750",
            "source_url": "/i6811419918387380750/",
            "display_url": "http://toutiao.com/group/6811419918387380750/",
            "is_stick": true,
            "item_id": "6811419918387380750",
            "repin_count": 306,
            "cell_flag": 262153,
            "source_open_url": "sslocal://profile?uid=4377795668",
            "level": 0,
            "digg_count": 890,
            "behot_time": 1585910522,
            "hot": 0,
            "cursor": 1585910522999,
            "url": "http://www.xinhuanet.com/politics/leaders/2020-04/03/c_1125811258.htm",
            "like_count": 1213,
            "user_repin": 0,
            "label_style": 1,
            "video_style": 0,
            "media_info": {
                "avatar_url": "http://p9.pstatp.com/large/ff1b0000332acf4a6c2e",
                "media_id": 4377795668,
                "name": "新华网客户端",
                "user_verified": true
            },
            "group_id": "6811419918387380750"
        },
        {
            "media_name": "央视网",
            "ban_comment": 0,
            "abstract": "“克服了危即是机”，习近平总书记始终心系复工复产。时隔十余年，习近平总书记又到余村，之江大地又传新语。“解决问题的宗旨，就是为人民服务。”",
            "image_list": [],
            "datetime": "2020-04-03 18:34",
            "article_type": 0,
            "tag": "news_politics",
            "has_m3u8_video": 0,
            "display_dt": 1585901582,
            "has_mp4_video": 0,
            "aggr_type": 1,
            "cell_type": 0,
            "article_sub_type": 0,
            "bury_count": 0,
            "title": "绘心绘语 | 春意浓，之江又传新语",
            "source_icon_style": 1,
            "tip": 0,
            "has_video": false,
            "share_url": "http://toutiao.com/a6811395432946598403/?app=news_article&is_hit_share_recommend=0",
            "label": "置顶",
            "source": "央视网",
            "comment_count": 63,
            "article_url": "http://toutiao.com/group/6811395432946598403/",
            "publish_time": 1585901582,
            "group_flags": 0,
            "has_image": false,
            "action_extra": "{\"channel_id\": 0}",
            "tag_id": "6811395432946598403",
            "source_url": "/i6811395432946598403/",
            "display_url": "http://toutiao.com/group/6811395432946598403/",
            "is_stick": true,
            "item_id": "6811395432946598403",
            "repin_count": 345,
            "cell_flag": 262153,
            "source_open_url": "sslocal://profile?uid=5949816472",
            "level": 0,
            "digg_count": 462,
            "behot_time": 1585910072,
            "hot": 0,
            "cursor": 1585910072999,
            "url": "http://toutiao.com/group/6811395432946598403/",
            "like_count": 803,
            "user_repin": 0,
            "label_style": 1,
            "video_style": 0,
            "media_info": {
                "avatar_url": "http://p1.pstatp.com/large/4d0004063a0a1de1f7",
                "media_id": 5949816472,
                "name": "央视网",
                "user_verified": true
            },
            "group_id": "6811395432946598403"
        },
        {
            "media_name": "北京日报客户端",
            "ban_comment": 0,
            "abstract": "最近，网传有一名海航空姐，执飞国际航班后在西安核酸检测为阳性，飞抵北京去向不明。4月3日，在北京市新型冠状病毒肺炎疫情防控工作新闻发布会上，市疾控中心副主任庞星火表示已经注意到相关网络信息。",
            "image_list": [],
            "datetime": "2020-04-03 18:27",
            "article_type": 0,
            "tag": "news_politics_general",
            "has_m3u8_video": 0,
            "display_dt": 1585903666,
            "has_mp4_video": 0,
            "aggr_type": 1,
            "cell_type": 0,
            "article_sub_type": 0,
            "bury_count": 0,
            "title": "海航空姐西安核酸检测阳性，飞抵北京去向不明？官方回应",
            "source_icon_style": 1,
            "tip": 1,
            "has_video": false,
            "share_url": "http://toutiao.com/a6811404382244962830/?app=news_article&is_hit_share_recommend=0",
            "source": "北京日报客户端",
            "comment_count": 361,
            "article_url": "http://toutiao.com/group/6811404382244962830/",
            "publish_time": 1585903666,
            "group_flags": 0,
            "middle_mode": true,
            "gallary_image_count": 1,
            "action_extra": "{\"channel_id\": 0}",
            "tag_id": "6811404382244962830",
            "source_url": "/i6811404382244962830/",
            "display_url": "http://toutiao.com/group/6811404382244962830/",
            "is_stick": false,
            "item_id": "6811404382244962830",
            "repin_count": 535,
            "cell_flag": 262155,
            "source_open_url": "sslocal://profile?uid=94231358279",
            "level": 0,
            "digg_count": 2035,
            "behot_time": 1585909622,
            "hot": 1,
            "cursor": 1585909622999,
            "url": "http://toutiao.com/group/6811404382244962830/",
            "like_count": 1957,
            "image_url": "http://p29-tt.byteimg.com/img/pgc-image/b4afb63de00f4a3eb6269d13573305d2~tplv-tt-cs0:640:360.jpg",
            "user_repin": 0,
            "has_image": true,
            "video_style": 0,
            "media_info": {
                "avatar_url": "http://p3.pstatp.com/large/66bd0002f4ac966aa1d9",
                "media_id": 1593723192644612,
                "name": "北京日报客户端",
                "user_verified": true
            },
            "group_id": "6811404382244962830"
        },
        {
            "media_name": "百晓生侃中国史",
            "ban_comment": 1,
            "abstract": "1998年冬天，湖北省咸宁市有一位名叫刘建光的小伙想要参军入伍，可是因为指标有限，刘建光与此次征兵无缘。",
            "image_list": [
                {
                    "url": "http://p9-tt-ipv6.byteimg.com/img/pgc-image/7137d8699e114e7e8164ee0b5c0cccdb~tplv-tt-cs0:640:360.jpg",
                    "width": 640,
                    "height": 360
                },
                {
                    "url": "http://p29-tt.byteimg.com/img/pgc-image/1083650d328a478ab7d093d70ad5b435~tplv-tt-cs0:402:297.jpg",
                    "width": 402,
                    "height": 226
                },
                {
                    "url": "http://p1-tt-ipv6.byteimg.com/img/pgc-image/c0276d9cd20746b2aa088046f5c0f165~tplv-tt-cs0:514:361.jpg",
                    "width": 514,
                    "height": 289
                }
            ],
            "datetime": "2020-04-03 18:19",
            "article_type": 0,
            "more_mode": true,
            "tag": "news_society",
            "has_m3u8_video": 0,
            "display_dt": 1585838781,
            "has_mp4_video": 0,
            "aggr_type": 1,
            "cell_type": 0,
            "article_sub_type": 0,
            "bury_count": 0,
            "title": "老人隐姓埋名43年，为孙子参军不得已亮明身份，后受邀赴北京观礼",
            "source_icon_style": 1,
            "tip": 0,
            "has_video": false,
            "share_url": "http://toutiao.com/a6811121968230695437/?app=news_article&is_hit_share_recommend=0",
            "source": "百晓生侃中国史",
            "comment_count": 0,
            "article_url": "http://toutiao.com/group/6811121968230695437/",
            "publish_time": 1585838781,
            "group_flags": 0,
            "gallary_image_count": 7,
            "action_extra": "{\"channel_id\": 0}",
            "tag_id": "6811121968230695437",
            "source_url": "/i6811121968230695437/",
            "display_url": "http://toutiao.com/group/6811121968230695437/",
            "is_stick": false,
            "item_id": "6811121968230695437",
            "repin_count": 60,
            "cell_flag": 262155,
            "source_open_url": "sslocal://profile?uid=2704447396646797",
            "level": 0,
            "digg_count": 501,
            "behot_time": 1585909172,
            "hot": 0,
            "cursor": 1585909172999,
            "url": "http://toutiao.com/group/6811121968230695437/",
            "like_count": 458,
            "user_repin": 0,
            "has_image": true,
            "video_style": 0,
            "media_info": {
                "avatar_url": "http://p3.pstatp.com/large/pgc-image/6763cbee8183498b9c1c415f9a085baf",
                "media_id": 1651725989842952,
                "name": "百晓生侃中国史",
                "user_verified": false
            },
            "group_id": "6811121968230695437"
        },
        {
            "media_name": "北晚新视觉网",
            "ban_comment": 0,
            "abstract": "记者昨天从市保障房中心获悉，为进一步落实公租房承租家庭实名登记备案制，本市对已入住的近6万户公租房家庭启动“云”端信息采集。资料图邓伟 摄根据《关于加强本市公共租赁住房建设和管理的通知》、《北京市公共租赁住房后期管理暂行办法》等文件规定，本市一直采取公共租赁住房入住家庭实名登记备",
            "image_list": [],
            "datetime": "2020-04-03 18:12",
            "article_type": 0,
            "tag": "news_house",
            "has_m3u8_video": 0,
            "display_dt": 1585894779,
            "has_mp4_video": 0,
            "aggr_type": 1,
            "cell_type": 0,
            "article_sub_type": 0,
            "bury_count": 0,
            "title": "微信小程序为公租房“云”备案，采集近6万户公租房家庭信息",
            "source_icon_style": 1,
            "tip": 0,
            "has_video": false,
            "share_url": "http://toutiao.com/group/6811366213378114062/?app=news_article&is_hit_share_recommend=0",
            "source": "北晚新视觉网",
            "comment_count": 0,
            "article_url": "http://www.takefoto.cn/viewnews-2103545.html",
            "publish_time": 1585894779,
            "group_flags": 0,
            "middle_mode": true,
            "gallary_image_count": 1,
            "action_extra": "{\"channel_id\": 0}",
            "tag_id": "6811366213378114062",
            "source_url": "/i6811366213378114062/",
            "display_url": "http://toutiao.com/group/6811366213378114062/",
            "is_stick": false,
            "item_id": "6811366213378114062",
            "repin_count": 0,
            "cell_flag": 262155,
            "source_open_url": "sslocal://profile?uid=5003463346",
            "level": 0,
            "digg_count": 0,
            "behot_time": 1585908722,
            "hot": 0,
            "cursor": 1585908722999,
            "url": "http://www.takefoto.cn/viewnews-2103545.html",
            "image_url": "http://p1-tt-ipv6.byteimg.com/img/pgc-image/Rv4eqIIFS7kKfz~tplv-tt-cs0:640:360.jpg",
            "user_repin": 0,
            "has_image": true,
            "video_style": 0,
            "media_info": {
                "avatar_url": "http://p3.pstatp.com/large/6655/4761617619",
                "media_id": 5003463346,
                "name": "北晚新视觉网",
                "user_verified": true
            },
            "group_id": "6811366213378114062"
        },
        {
            "media_name": "海峡要闻",
            "ban_comment": 0,
            "abstract": "而美国，西班牙，意大利这些国家疫情如此严重就是因为这些国家的民众从一开始没有引起足够的重视，反而认为中国对人员进行有效的隔离是侵犯人权，他们照样参加公共活动，其实他们的行为就为现在被确诊的人数越来越多，埋下了隐患。",
            "image_list": [],
            "datetime": "2020-04-03 18:04",
            "article_type": 0,
            "tag": "news_world",
            "has_m3u8_video": 0,
            "display_dt": 1585896941,
            "has_mp4_video": 0,
            "aggr_type": 1,
            "cell_type": 0,
            "article_sub_type": 0,
            "bury_count": 0,
            "title": "\"口罩停止发货\"！西班牙采购物资拒绝付款，中方霸气回击",
            "source_icon_style": 1,
            "tip": 0,
            "has_video": false,
            "share_url": "http://toutiao.com/a6811375497818145293/?app=news_article&is_hit_share_recommend=0",
            "source": "海峡要闻",
            "comment_count": 223,
            "article_url": "http://toutiao.com/group/6811375497818145293/",
            "publish_time": 1585896941,
            "group_flags": 0,
            "middle_mode": true,
            "gallary_image_count": 4,
            "action_extra": "{\"channel_id\": 0}",
            "tag_id": "6811375497818145293",
            "source_url": "/i6811375497818145293/",
            "display_url": "http://toutiao.com/group/6811375497818145293/",
            "is_stick": false,
            "item_id": "6811375497818145293",
            "repin_count": 103,
            "cell_flag": 262155,
            "source_open_url": "sslocal://profile?uid=1068358403104631",
            "level": 0,
            "digg_count": 781,
            "behot_time": 1585908272,
            "hot": 0,
            "cursor": 1585908272999,
            "url": "http://toutiao.com/group/6811375497818145293/",
            "like_count": 798,
            "image_url": "http://p6-tt-ipv6.byteimg.com/img/pgc-image/0fc6ceda175046a7ab95270ad7e4c4f2~tplv-tt-cs0:640:360.jpg",
            "user_repin": 0,
            "has_image": true,
            "video_style": 0,
            "media_info": {
                "avatar_url": "http://p8.pstatp.com/large/pgc-image/da6b63ed3b894e22b20205b99d99d68c",
                "media_id": 1647702720651278,
                "name": "海峡要闻",
                "user_verified": true
            },
            "group_id": "6811375497818145293"
        },
        {
            "video_id": "v020047e0000bpdnb3s9hq5jogl8qlb0",
            "media_name": "二姐爱美食",
            "ban_comment": 0,
            "abstract": "我家胡萝卜从不炒着吃，加2个鸡蛋，简单几步，上桌5斤不够吃，香",
            "video_detail_info": {
                "detail_video_large_image": {
                    "url": "http://p29-tt.byteimg.com/img/tos-cn-i-0004/ff0f20158a634f36828f1545bcc2c4de~tplv-tt-cs0:640:360.jpg",
                    "width": 640,
                    "height": 360
                },
                "video_id": "v020047e0000bpdnb3s9hq5jogl8qlb0",
                "video_watch_count": 482429,
                "group_flags": 32832,
                "direct_play": 1
            },
            "image_list": [],
            "datetime": "2020-04-03 17:57",
            "article_type": 0,
            "tag": "video_motherbaby",
            "has_m3u8_video": 0,
            "video_duration": 193,
            "display_dt": 1583052810,
            "has_mp4_video": 0,
            "aggr_type": 1,
            "cell_type": 0,
            "article_sub_type": 0,
            "bury_count": 12,
            "title": "春天多给孩子吃这小饼，无油无水，常吃眼睛明亮长的高，太好吃了",
            "source_icon_style": 1,
            "tip": 0,
            "has_video": true,
            "share_url": "https://m.toutiaoimg.cn/a6799160047210332684/?app=news_article&is_hit_share_recommend=0",
            "source": "二姐爱美食",
            "comment_count": 193,
            "article_url": "http://toutiao.com/group/6799160047210332684/",
            "large_mode": true,
            "large_image_url": "http://p9-tt-ipv6.byteimg.com/img/tos-cn-i-0004/ff0f20158a634f36828f1545bcc2c4de~tplv-tt-cs0:640:360.jpg",
            "publish_time": 1583052810,
            "group_flags": 32833,
            "action_extra": "{\"channel_id\": 0}",
            "tag_id": "6799160047210332684",
            "source_url": "/i6799160047210332684/",
            "display_url": "http://toutiao.com/group/6799160047210332684/",
            "is_stick": false,
            "item_id": "6799160047210332684",
            "repin_count": 13365,
            "cell_flag": 262155,
            "source_open_url": "sslocal://profile?refer=video&uid=63969948610",
            "level": 0,
            "digg_count": 4961,
            "behot_time": 1585907822,
            "hot": 0,
            "cursor": 1585907822999,
            "url": "http://toutiao.com/group/6799160047210332684/",
            "user_repin": 0,
            "has_image": false,
            "video_style": 0,
            "media_info": {
                "avatar_url": "http://p1.pstatp.com/large/pgc-image/23414a2b416844a7b3b40ca7dadee553",
                "media_id": 1575804500973581,
                "name": "二姐爱美食",
                "user_verified": true
            },
            "group_id": "6799160047210332684"
        },
        {
            "media_name": "阿荔文史",
            "ban_comment": 0,
            "abstract": "然而当他身患重病久治不愈，倍感时日无多后，便服用了红丸，谁知服下第一颗，身体虽略有好转，但等第二颗服下没多久，便当即暴毙。",
            "image_list": [
                {
                    "url": "http://p29-tt.byteimg.com/img/pgc-image/7b31b79e9e0d48e99cce4037421833ad~tplv-tt-cs0:640:360.jpg",
                    "width": 640,
                    "height": 360
                },
                {
                    "url": "http://p9-tt-ipv6.byteimg.com/img/pgc-image/3f3fa604616748c48ae1d15bcf5b2ea6~tplv-tt-cs0:640:360.jpg",
                    "width": 640,
                    "height": 360
                },
                {
                    "url": "http://p29-tt.byteimg.com/img/pgc-image/cf97af91b5c4474393d9b816d13fead9~tplv-tt-cs0:640:360.jpg",
                    "width": 640,
                    "height": 360
                }
            ],
            "datetime": "2020-04-03 17:49",
            "article_type": 0,
            "more_mode": true,
            "tag": "news",
            "has_m3u8_video": 0,
            "display_dt": 1585825294,
            "has_mp4_video": 0,
            "aggr_type": 1,
            "cell_type": 0,
            "article_sub_type": 0,
            "bury_count": 0,
            "title": "中国第一例女冷冻人，希望50年后解冻复活和家人团聚，如今怎样？",
            "source_icon_style": 1,
            "tip": 0,
            "has_video": false,
            "share_url": "http://toutiao.com/a6811067068448768523/?app=news_article&is_hit_share_recommend=0",
            "source": "阿荔文史",
            "comment_count": 77,
            "article_url": "http://toutiao.com/group/6811067068448768523/",
            "publish_time": 1585825294,
            "group_flags": 0,
            "gallary_image_count": 7,
            "action_extra": "{\"channel_id\": 0}",
            "tag_id": "6811067068448768523",
            "source_url": "/i6811067068448768523/",
            "display_url": "http://toutiao.com/group/6811067068448768523/",
            "is_stick": false,
            "item_id": "6811067068448768523",
            "repin_count": 135,
            "cell_flag": 262155,
            "source_open_url": "sslocal://profile?uid=417440780004983",
            "level": 0,
            "digg_count": 1100,
            "behot_time": 1585907372,
            "hot": 0,
            "cursor": 1585907372999,
            "url": "http://toutiao.com/group/6811067068448768523/",
            "like_count": 842,
            "user_repin": 0,
            "has_image": true,
            "video_style": 0,
            "media_info": {
                "avatar_url": "http://p1.pstatp.com/large/pgc-image/4e6668b419304596943483726f5b4aee",
                "media_id": 1645975576321036,
                "name": "阿荔文史",
                "user_verified": true
            },
            "group_id": "6811067068448768523"
        },
        {
            "media_name": "成都日报锦观",
            "ban_comment": 0,
            "abstract": "刚搬迁入住时，邻里关系重组，社区居民显得迷茫而焦躁，社区民警下社区开展工作，居民不愿意配合，真正是“门难进、人难找”，在当时群众的眼中，派出所是“你们的派出所”，社区是“你们的社区”。成都日报·锦观新闻记者 何良 供图 金牛公安 编辑 王戬 校对 王鹃",
            "image_list": [],
            "datetime": "2020-04-03 17:42",
            "article_type": 0,
            "tag": "news_society",
            "has_m3u8_video": 0,
            "display_dt": 1585909036,
            "has_mp4_video": 0,
            "aggr_type": 1,
            "cell_type": 0,
            "article_sub_type": 0,
            "bury_count": 0,
            "title": "成都社区民警谢和平：群众口中一字之差 就能体现工作的意义",
            "source_icon_style": 1,
            "tip": 0,
            "has_video": false,
            "share_url": "http://toutiao.com/a6811427447200809484/?app=news_article&is_hit_share_recommend=0",
            "source": "成都日报锦观",
            "comment_count": 0,
            "article_url": "http://toutiao.com/group/6811427447200809484/",
            "publish_time": 1585909036,
            "group_flags": 0,
            "middle_mode": true,
            "gallary_image_count": 3,
            "action_extra": "{\"channel_id\": 0}",
            "tag_id": "6811427447200809484",
            "source_url": "/i6811427447200809484/",
            "display_url": "http://toutiao.com/group/6811427447200809484/",
            "is_stick": false,
            "item_id": "6811427447200809484",
            "repin_count": 0,
            "cell_flag": 262155,
            "source_open_url": "sslocal://profile?uid=4390240706",
            "level": 0,
            "digg_count": 0,
            "behot_time": 1585906922,
            "hot": 0,
            "cursor": 1585906922999,
            "url": "http://toutiao.com/group/6811427447200809484/",
            "image_url": "http://p29-tt.byteimg.com/img/pgc-image/1a714e21889e4ec28e7ef1763aa7d43d~tplv-tt-cs0:640:360.jpg",
            "user_repin": 0,
            "has_image": true,
            "video_style": 0,
            "media_info": {
                "avatar_url": "http://p5a.pstatp.com/large/ffed00002d6df1474769",
                "media_id": 4470600037,
                "name": "成都日报锦观",
                "user_verified": true
            },
            "group_id": "6811427447200809484"
        },
        {
            "media_name": "39健康网",
            "ban_comment": 0,
            "abstract": "30岁的张贤是5年的尿毒症患者。“确诊尿毒症的那天，我一个人走去海边，准备去寻死。我家里没有人得过这种病，为什么我就这么倒霉摊上这种病呢！反正也好不了了，只能每天透析等死。”回忆25岁的那年冬天，张贤还瑟瑟发抖。“幸好，冰冻的海水救了我，那浩瀚无边的海浪拍醒了我。",
            "image_list": [],
            "datetime": "2020-04-03 17:34",
            "article_type": 0,
            "tag": "news_health",
            "has_m3u8_video": 0,
            "keywords": "药物,尿毒症,高血压,肾功能,31岁男子患上尿毒症,肾病",
            "display_dt": 1572485440,
            "has_mp4_video": 0,
            "aggr_type": 1,
            "cell_type": 0,
            "article_sub_type": 0,
            "bury_count": 18,
            "title": "为什么“尿毒症”越来越多？医生劝说：5个原因别碰，肾会感谢你",
            "source_icon_style": 1,
            "tip": 0,
            "has_video": false,
            "share_url": "http://toutiao.com/a6753429047511876100/?app=news_article&is_hit_share_recommend=0",
            "source": "39健康网",
            "comment_count": 2835,
            "article_url": "http://toutiao.com/group/6753429047511876100/",
            "publish_time": 1572485440,
            "group_flags": 0,
            "middle_mode": true,
            "gallary_image_count": 8,
            "action_extra": "{\"channel_id\": 0}",
            "tag_id": "6753429047511876100",
            "source_url": "/i6753429047511876100/",
            "display_url": "http://toutiao.com/group/6753429047511876100/",
            "is_stick": false,
            "item_id": "6753429047511876100",
            "repin_count": 35453,
            "cell_flag": 262155,
            "source_open_url": "sslocal://profile?uid=3414105634",
            "level": 0,
            "digg_count": 127402,
            "behot_time": 1585906472,
            "hot": 0,
            "cursor": 1585906472999,
            "url": "http://toutiao.com/group/6753429047511876100/",
            "like_count": 94523,
            "image_url": "http://p29-tt.byteimg.com/img/pgc-image/b99aa3b89b70430e812534ff45ab7b47~tplv-tt-cs0:640:360.jpg",
            "user_repin": 0,
            "has_image": true,
            "video_style": 0,
            "media_info": {
                "avatar_url": "http://p3.pstatp.com/large/pgc-image/7e361166c67d40b0875c15a4a08d1727",
                "media_id": 3430114949,
                "name": "39健康网",
                "user_verified": true
            },
            "group_id": "6753429047511876100"
        },
        {
            "media_name": "前线杂志",
            "ban_comment": 0,
            "abstract": "毛主席的生活收支报表作者 葛长银编辑 高斌毛泽东的一生自始至终都没有离开过记账活动。",
            "image_list": [
                {
                    "url": "http://p26-tt.byteimg.com/img/pgc-image/9194fe16887f44279cce642164691115~tplv-tt-cs0:640:360.jpg",
                    "width": 640,
                    "height": 360
                },
                {
                    "url": "http://p1-tt-ipv6.byteimg.com/img/pgc-image/7ae7b4ed9edf4dbf82901d2e4428c2d8~tplv-tt-cs0:513:746.jpg",
                    "width": 513,
                    "height": 288
                },
                {
                    "url": "http://p9-tt-ipv6.byteimg.com/img/pgc-image/50eb49da4ce948e09f677d8b81631ee3~tplv-tt-cs0:505:722.jpg",
                    "width": 505,
                    "height": 284
                }
            ],
            "datetime": "2020-04-03 17:27",
            "article_type": 0,
            "more_mode": true,
            "tag": "news_history",
            "has_m3u8_video": 0,
            "keywords": "毛顺生,王淑兰,延安,回忆毛主席在延安,毛泽民,毛泽东",
            "display_dt": 1573641938,
            "has_mp4_video": 0,
            "aggr_type": 1,
            "cell_type": 0,
            "article_sub_type": 0,
            "bury_count": 0,
            "title": "毛泽东的账簿：计家计国计天下",
            "source_icon_style": 1,
            "tip": 0,
            "has_video": false,
            "share_url": "http://toutiao.com/a6758740662633366019/?app=news_article&is_hit_share_recommend=0",
            "source": "前线杂志",
            "comment_count": 5102,
            "article_url": "http://toutiao.com/group/6758740662633366019/",
            "publish_time": 1573641938,
            "group_flags": 0,
            "gallary_image_count": 4,
            "action_extra": "{\"channel_id\": 0}",
            "tag_id": "6758740662633366019",
            "source_url": "/i6758740662633366019/",
            "display_url": "http://toutiao.com/group/6758740662633366019/",
            "is_stick": false,
            "item_id": "6758740662633366019",
            "repin_count": 7513,
            "cell_flag": 262155,
            "source_open_url": "sslocal://profile?uid=70255394677",
            "level": 0,
            "digg_count": 14054,
            "behot_time": 1585906022,
            "hot": 0,
            "cursor": 1585906022999,
            "url": "http://toutiao.com/group/6758740662633366019/",
            "like_count": 12446,
            "user_repin": 0,
            "has_image": true,
            "video_style": 0,
            "media_info": {
                "avatar_url": "http://p10.pstatp.com/large/6eea0004c539d3d01fc6",
                "media_id": 1594713916209156,
                "name": "前线杂志",
                "user_verified": true
            },
            "group_id": "6758740662633366019"
        },
        {
            "media_name": "桔子娱乐酱儿",
            "ban_comment": 0,
            "abstract": "对于很多人来说，能够长得高一点是非常幸运的一件事，因为身高对大家来说，已经成了一个最基本且重要的婚恋条件。",
            "image_list": [
                {
                    "url": "http://p9-tt-ipv6.byteimg.com/img/pgc-image/09c1d8c1db11428d91f4f053a68a6fa3~tplv-tt-cs0:640:360.jpg",
                    "width": 640,
                    "height": 360
                },
                {
                    "url": "http://p6-tt-ipv6.byteimg.com/img/pgc-image/29f85616e21648cd9dd084c36ef6dc8b~tplv-tt-cs0:640:410.jpg",
                    "width": 640,
                    "height": 410
                },
                {
                    "url": "http://p29-tt.byteimg.com/img/pgc-image/7b2948446e1b44f0abc2f56b415bd035~tplv-tt-cs0:640:426.jpg",
                    "width": 640,
                    "height": 360
                }
            ],
            "datetime": "2020-04-03 17:19",
            "article_type": 0,
            "more_mode": true,
            "tag": "news",
            "has_m3u8_video": 0,
            "display_dt": 1583579393,
            "has_mp4_video": 0,
            "aggr_type": 1,
            "cell_type": 0,
            "article_sub_type": 0,
            "bury_count": 8,
            "title": "2米巨人56岁娶28岁女友，娶妻生娃后的他，今状况如何？",
            "source_icon_style": 1,
            "tip": 0,
            "has_video": false,
            "share_url": "http://toutiao.com/a6801421702740836877/?app=news_article&is_hit_share_recommend=0",
            "source": "桔子娱乐酱儿",
            "comment_count": 192,
            "article_url": "http://toutiao.com/group/6801421702740836877/",
            "publish_time": 1583579393,
            "group_flags": 0,
            "gallary_image_count": 10,
            "action_extra": "{\"channel_id\": 0}",
            "tag_id": "6801421702740836877",
            "source_url": "/i6801421702740836877/",
            "display_url": "http://toutiao.com/group/6801421702740836877/",
            "is_stick": false,
            "item_id": "6801421702740836877",
            "repin_count": 5402,
            "cell_flag": 262155,
            "source_open_url": "sslocal://profile?uid=927631864773006",
            "level": 0,
            "digg_count": 44467,
            "behot_time": 1585905572,
            "hot": 0,
            "cursor": 1585905572999,
            "url": "http://toutiao.com/group/6801421702740836877/",
            "like_count": 32474,
            "user_repin": 0,
            "has_image": true,
            "video_style": 0,
            "media_info": {
                "avatar_url": "http://p9.pstatp.com/large/pgc-image/9d6a9ef778204bcaa92d9191618149e8",
                "media_id": 1650516359450632,
                "name": "桔子娱乐酱儿",
                "user_verified": true
            },
            "group_id": "6801421702740836877"
        },
        {
            "media_name": "中国青年网",
            "ban_comment": 0,
            "abstract": "·从左至右依次是安倍洋子、安倍晋三、安倍昭惠到后来，两个人直接开始打嘴仗，这边昭惠说：“我们家有四口人，安倍和我，还有一位老妇人和一条狗。”",
            "image_list": [
                {
                    "url": "http://p26-tt.byteimg.com/img/pgc-image/Run0wzy2hWs9RQ~tplv-tt-cs0:640:360.jpg",
                    "width": 640,
                    "height": 360
                },
                {
                    "url": "http://p26-tt.byteimg.com/img/pgc-image/Run0x0hHPcnTNy~tplv-tt-cs0:641:679.jpg",
                    "width": 641,
                    "height": 360
                },
                {
                    "url": "http://p29-tt.byteimg.com/img/pgc-image/Run0x1DIUAhyRX~tplv-tt-cs0:562:372.jpg",
                    "width": 562,
                    "height": 316
                }
            ],
            "datetime": "2020-04-03 17:12",
            "article_type": 1,
            "more_mode": true,
            "tag": "news_world",
            "has_m3u8_video": 0,
            "display_dt": 1585634077,
            "has_mp4_video": 0,
            "aggr_type": 1,
            "cell_type": 0,
            "article_sub_type": 1,
            "bury_count": 0,
            "title": "疫情凶猛，首相夫人却组团赏樱！开酒馆、闹丑闻、迷小鲜肉，安倍后院要“失火”？",
            "source_icon_style": 1,
            "tip": 0,
            "has_video": false,
            "share_url": "http://toutiao.com/group/6810246507216765453/?app=news_article&is_hit_share_recommend=0",
            "source": "中国青年网",
            "comment_count": 59,
            "article_url": "http://t.m.youth.cn/transfer/toutiao/url/3g.youth.cn/rdzx/202003/t20200331_12264416.htm",
            "publish_time": 1585634077,
            "group_flags": 0,
            "gallary_image_count": 26,
            "action_extra": "{\"channel_id\": 0}",
            "tag_id": "6810246507216765453",
            "source_url": "/item/6810246507216765453/",
            "display_url": "http://toutiao.com/group/6810246507216765453/",
            "is_stick": false,
            "item_id": "6810246507216765453",
            "repin_count": 1544,
            "cell_flag": 262155,
            "source_open_url": "sslocal://profile?uid=3582660809",
            "level": 0,
            "digg_count": 13619,
            "behot_time": 1585905122,
            "hot": 0,
            "cursor": 1585905122999,
            "url": "http://t.m.youth.cn/transfer/toutiao/url/3g.youth.cn/rdzx/202003/t20200331_12264416.htm",
            "like_count": 8224,
            "user_repin": 0,
            "has_image": true,
            "video_style": 0,
            "media_info": {
                "avatar_url": "http://p2.pstatp.com/thumb/1398/4664054183",
                "media_id": 3583449547,
                "name": "中国青年网",
                "user_verified": true
            },
            "group_id": "6810246507216765453"
        },
        {
            "video_id": "v02004010000bpvd6vd7gl1hand2oh1g",
            "media_name": "摩托车之家",
            "ban_comment": 0,
            "abstract": "本田Crf450R越野场地耐力骑行比赛，冲坡飞这么高太恐怖了",
            "video_detail_info": {
                "detail_video_large_image": {
                    "url": "http://p1-tt-ipv6.byteimg.com/img/tos-cn-p-0026/e67177afac2197f01f8d583c79633ccc~tplv-tt-cs0:640:360.jpg",
                    "width": 640,
                    "height": 360
                },
                "video_id": "v02004010000bpvd6vd7gl1hand2oh1g",
                "video_watch_count": 58,
                "group_flags": 32832,
                "direct_play": 1
            },
            "image_list": [],
            "datetime": "2020-04-03 17:04",
            "article_type": 0,
            "tag": "video_sports",
            "has_m3u8_video": 0,
            "video_duration": 1064,
            "display_dt": 1585888200,
            "has_mp4_video": 0,
            "aggr_type": 1,
            "cell_type": 0,
            "article_sub_type": 0,
            "bury_count": 0,
            "title": "本田Crf450R越野场地耐力骑行比赛，冲坡飞这么高太恐怖了",
            "source_icon_style": 1,
            "tip": 0,
            "has_video": true,
            "share_url": "https://m.toutiaoimg.cn/a6809120755561792014/?app=news_article&is_hit_share_recommend=0",
            "source": "摩托车之家",
            "comment_count": 0,
            "article_url": "http://toutiao.com/group/6809120755561792014/",
            "large_mode": true,
            "large_image_url": "http://p9-tt-ipv6.byteimg.com/img/tos-cn-p-0026/e67177afac2197f01f8d583c79633ccc~tplv-tt-cs0:640:360.jpg",
            "publish_time": 1585888200,
            "group_flags": 32832,
            "action_extra": "{\"channel_id\": 0}",
            "tag_id": "6809120755561792014",
            "source_url": "/i6809120755561792014/",
            "display_url": "http://toutiao.com/group/6809120755561792014/",
            "is_stick": false,
            "item_id": "6809120755561792014",
            "repin_count": 0,
            "cell_flag": 262155,
            "source_open_url": "sslocal://profile?refer=video&uid=6306166476",
            "level": 0,
            "digg_count": 0,
            "behot_time": 1585904672,
            "hot": 0,
            "cursor": 1585904672999,
            "url": "http://toutiao.com/group/6809120755561792014/",
            "user_repin": 0,
            "has_image": false,
            "video_style": 0,
            "media_info": {
                "avatar_url": "http://p4.pstatp.com/large/6edc00052dcb4781738f",
                "media_id": 6306236436,
                "name": "摩托车之家",
                "user_verified": true
            },
            "group_id": "6809120755561792014"
        },
        {
            "media_name": "中国新闻网",
            "ban_comment": 0,
            "abstract": "美石油巨头股价一年跌去98.84% 惠廷公司当地时间4月1日宣布，已向美国德克萨斯州南区破产法院申请第11章破产保护，促使其股票在纽约证券交易所停牌。    惠廷公司股价仅31美分。",
            "image_list": [
                {
                    "url": "http://p29-tt.byteimg.com/img/pgc-image/Rv5W2h2E9QAeqZ~tplv-tt-cs0:640:360.jpg",
                    "width": 640,
                    "height": 360
                },
                {
                    "url": "http://p29-tt.byteimg.com/img/pgc-image/Rv5W2hT4xOyeS2~tplv-tt-cs0:669:383.jpg",
                    "width": 669,
                    "height": 383
                },
                {
                    "url": "http://p29-tt.byteimg.com/img/pgc-image/Rv5W2hpR7zNLE~tplv-tt-cs0:500:333.jpg",
                    "width": 500,
                    "height": 281
                }
            ],
            "datetime": "2020-04-03 16:57",
            "article_type": 0,
            "more_mode": true,
            "tag": "news_finance",
            "has_m3u8_video": 0,
            "display_dt": 1585907452,
            "has_mp4_video": 0,
            "aggr_type": 1,
            "cell_type": 0,
            "article_sub_type": 0,
            "bury_count": 0,
            "title": "美油企或迎破产潮，特朗普干预致油价暴涨，还能涨多少？",
            "source_icon_style": 1,
            "tip": 0,
            "has_video": false,
            "share_url": "http://toutiao.com/group/6811420644169744904/?app=news_article&is_hit_share_recommend=0",
            "source": "中国新闻网",
            "comment_count": 1,
            "article_url": "http://hz.m.chinanews.com/wapapp/toutiao/cj/2020/04-03/9146943.shtml",
            "publish_time": 1585907452,
            "group_flags": 0,
            "gallary_image_count": 4,
            "action_extra": "{\"channel_id\": 0}",
            "tag_id": "6811420644169744904",
            "source_url": "/i6811420644169744904/",
            "display_url": "http://toutiao.com/group/6811420644169744904/",
            "is_stick": false,
            "item_id": "6811420644169744904",
            "repin_count": 0,
            "cell_flag": 262155,
            "source_open_url": "sslocal://profile?uid=5757091251",
            "level": 0,
            "digg_count": 0,
            "behot_time": 1585904222,
            "hot": 0,
            "cursor": 1585904222999,
            "url": "http://hz.m.chinanews.com/wapapp/toutiao/cj/2020/04-03/9146943.shtml",
            "like_count": 1,
            "user_repin": 0,
            "has_image": true,
            "video_style": 0,
            "media_info": {
                "avatar_url": "http://p3.pstatp.com/large/97d001bf3f3cba72913",
                "media_id": 50098085017,
                "name": "中国新闻网",
                "user_verified": true
            },
            "group_id": "6811420644169744904"
        }
    ],
    "return_count": 15,
    "html": null,
    "page_id": "/__all__/"
    }